flask_kdb/__init__.py
Flask_kdb-1.0.0.dist-info/LICENSE.md
Flask_kdb-1.0.0.dist-info/METADATA
Flask_kdb-1.0.0.dist-info/WHEEL
Flask_kdb-1.0.0.dist-info/top_level.txt
Flask_kdb-1.0.0.dist-info/RECORD
