Metadata-Version: 2.1
Name: Flask-kdb
Version: 1.0.0
Summary: kdb+ connections within a Flask application.
Home-page: http://www.github.com/ryanmcfarland/flask-kdb/
Author: Ryan McFarland
Author-email: ryanmcfarland@outlook.com
License: MIT License
Keywords: flask,kdb,kdb+,q,qpython
Platform: UNKNOWN
Classifier: Development Status :: 3 - Alpha
Classifier: Environment :: Web Environment
Classifier: Intended Audience :: Developers
Classifier: License :: OSI Approved :: MIT License
Classifier: Framework :: Flask
Classifier: Operating System :: MacOS
Classifier: Operating System :: Microsoft :: Windows
Classifier: Operating System :: POSIX
Classifier: Operating System :: Unix
Classifier: Programming Language :: Python
Classifier: Programming Language :: Python :: 3
Classifier: Topic :: Internet :: WWW/HTTP :: Dynamic Content
Classifier: Topic :: Software Development :: Libraries :: Python Modules
Classifier: Topic :: Software Development
Requires-Dist: Flask (>=2.0.2)
Requires-Dist: numpy (>=1.8.0)
Requires-Dist: qPython3 (>=1.0.0)
